AUTHORS
CHANGELOG.rst
LICENSE
MANIFEST.in
README
README.rst
requirements.txt
setup.cfg
setup.py
black_hole_solver/__init__.py
black_hole_solver/__main__.py
black_hole_solver/template.py
black_hole_solver.egg-info/PKG-INFO
black_hole_solver.egg-info/SOURCES.txt
black_hole_solver.egg-info/dependency_links.txt
black_hole_solver.egg-info/not-zip-safe
black_hole_solver.egg-info/requires.txt
black_hole_solver.egg-info/top_level.txt
docs/CHANGELOG.rst
docs/CONTRIBUTING.rst
docs/LICENSE.rst
docs/README.rst
docs/conf.py
docs/index.rst
docs/html/index.html
tests/__init__.py
tests/test_bhs.py
tests/test_sanity.py