Metadata-Version: 2.1
Name: black_hole_solver
Version: 0.2.4
Summary: Solve Golf and Black Hole solitaires
Home-page: https://github.com/shlomif/black_hole_solver
Author: Shlomi Fish
Author-email: shlomif@cpan.org
License: 3-clause BSD
Keywords: black_hole_solver
Platform: any
Classifier: Development Status :: 1 - Planning
Classifier: Programming Language :: Python
Classifier: Programming Language :: Python :: 3
Classifier: Programming Language :: Python :: 3.6
Classifier: Programming Language :: Python :: 3.7
Classifier: Programming Language :: Python :: 3.8
Classifier: Programming Language :: Python :: 3.9
Classifier: Programming Language :: Python :: 3.10
Classifier: Programming Language :: Python :: 3.11
License-File: LICENSE
License-File: AUTHORS
Requires-Dist: cffi
Requires-Dist: coverage
Requires-Dist: pysol_cards
Requires-Dist: pytest
Requires-Dist: pytest-cov
Requires-Dist: requests
Requires-Dist: twine
